setup.py
singleheap.c
faerie/__init__.py
faerie.egg-info/PKG-INFO
faerie.egg-info/SOURCES.txt
faerie.egg-info/dependency_links.txt
faerie.egg-info/entry_points.txt
faerie.egg-info/requires.txt
faerie.egg-info/top_level.txt
faerie/faerie/__init__.py
faerie/faerie/faerie.py
faerie/faerie/test.py