Metadata-Version: 1.0
Name: faerie
Version: 1.1.3
Summary: Dictionary-based entity extraction with efficient filtering
Home-page: https://github.com/usc-isi-i2/dig-dictionary-extraction/
Author: Zheng Tang
Author-email: zhengtan@isi.edu
License: UNKNOWN
Keywords: heap,entity_extraction
Platform: UNKNOWN
